Workbook

Sheet Sheet1
B2: A Study of the Proposed Acquisition of Bandhan Bank by Axis Bank
B5: Strategic Rationale, Valuation & EPS Impact Analysis
B10: Prepared By | C10: Bhavook Wadhwa
B11: Programme | C11: PGDM (Post Graduate Diploma in Management) — Finance
B12: Institution | C12: Welingkar Institute of Management, Mumbai
B13: Project Type | C13: Independent Academic Project (Mergers & Acquisitions)
B14: Date | C14: September 2026
B16: ABOUT THIS PROJECT
B17: This workbook models a hypothetical acquisition of Bandhan Bank by Axis Bank, built as part of my PGDM coursework in Finance at Welingkar Institute of Management, Mumbai. It covers deal valuation, the funding structure of the transaction, and the resulting accretion / dilution impact on Axis Bank's earnings per share (EPS), along with supporting visuals and a one-page deal memo summarising the analysis.
B23: WORKBOOK GUIDE
B24: Sheet | C24: Contents
B25: Introduction | C25: This cover sheet — project details, workbook guide, and disclaimer.
B26: M&A Model | C26: Core deal model — valuation, purchase price, share exchange ratio, and combined-entity financials.
B27: Funding the deal | C27: Sources of funds for the transaction — equity (share swap), Tier-II debt, and cash.
B28: Findings | C28: Conclusions drawn from the model.
B29: Visuals | C29: Funding-mix donut chart and EPS-impact waterfall chart, with supporting data tables.
B31: DISCLAIMER
B32: This document is an independent academic exercise prepared solely for learning purposes as part of a PGDM (Finance) project at Welingkar Institute of Management, Mumbai. It is not affiliated with, endorsed by, or reviewed by Axis Bank, Bandhan Bank, or any of their officers, employees, or advisors. All figures, assumptions, and conclusions are the author's own estimates, built on publicly available information and simplified for illustrative purposes; they do not represent an actual or proposed transaction between the two banks. Nothing in this workbook constitutes investment advice, a recommendation, or an offer to buy or sell any security, and it should not be relied upon for any financial, legal, or investment decision. Please verify all data independently before any other use.

Sheet M&A Model
B1: Axis Bank (Acquirer) | C1: Bandhan Bank (Target)
A2: Current Share Price ₹ | B2: 1242.7 | C2: 184.7
A3: Shares Outstanding (Cr) | B3: 311 | C3: 161
A4: Net Income (FY26, , ₹ Cr) | B4: 27773 | C4: 1353
A6: Deal Assumptions
A7: TakeOver Premium (%) | C7: 0.25
A8: Offer Price Per Share (₹) | C8: =(C2*(1+C7)) -> 230.875
A9: Total Purchase Price (₹ Cr) | C9: =C8*C3 -> 37170.875
A11: Funding Schedul
A12: Cash % | B12: 0.05 | C12: =$C$9*B12 -> 1858.5438
A13: Debt % | B13: 0.05 | C13: =$C$9*B13 -> 1858.5438
A14: Equity % | B14: 0.9 | C14: =$C$9*B14 -> 33453.787
A15: Interest Forgone on Cash | B15: 0.05
A16: Pre Tax Cost of Debt | B16: 0.078
A17: Corporate Tax Rate (%) | B17: 0.252
A19: New Shares Issued (Cr) | C19: =C14/$B$2 -> 26.920244
A21: Combined Income Statement
A22: Axis Bank Net Income | C22: =B4 -> 27773
A23: Bandhan Bank Net Income | C23: =C4 -> 1353
A24: Less: Interest Foregone on Cash (Post-Tax) | C24: =(C12*B15)*(1-$B$17) -> 69.509536
A25: Less: Interest Expense on New Debt (Post-Tax) | C25: =(C13*B16)*(1-$B$17) -> 108.43488
A26: Combined Net Income | C26: =C22+C23-C24-C25 -> 28948.056
A28: Accretion / (Dilution) Analysis
A29: Axis Bank Standalone EPS | C29: =B4/B3 -> 89.302251
A30: Combined Shares Outstanding (Cr) | C30: =B3+C19 -> 337.92024
A31: Combined EPS | C31: =C26/C30 -> 85.665349
A32: Accretion / (Dilution) (₹) | C32: =C31-C29 -> -3.636902
A33: Accretion / (Dilution) (%) | C33: =C32/C29 -> -0.04072576

Sheet Funding the deal
A1: Step1: Funding mix
A2: Cash Equivalents (Cr) | B2: 78627
A3: Total Purchase Price (₹ Cr) | B3: ='M&A Model'!C8*'M&A Model'!C3 -> 37170.875
A4: Extra Reserve | B4: =B2-B3 -> 41456.125
A6: Step2: Cost of Debt (Pre-Tax) | B6: 0.078
A8: Step3: Interest Foregone on Cash
A9: Standing Deposit Facility Rate | B9: 0.05
A10: Reverese Repo Rate | B10: 0.0335
A13: Equity | B13: 0.9
A14: Debt | B14: 0.05
A15: Cash | B15: 0.05

Sheet Findings
A1: Findings

Sheet Visuals
A1: Visual 1: Funding Mix (Donut Chart)
A3: Funding Source | B3: % of Total | C3: ₹ Cr
A4: Equity (Share Swap) | B4: =Visuals!$F$4 -> 0.9 | C4: ='M&A Model'!C14 -> 33453.787 | F4: ='M&A Model'!B14 -> 0.9
A5: Tier-II Debt | B5: =Visuals!$F$5 -> 0.05 | C5: ='M&A Model'!C13 -> 1858.5438 | F5: ='M&A Model'!B13 -> 0.05
A6: Cash | B6: =Visuals!$F$6 -> 0.05 | C6: ='M&A Model'!C12 -> 1858.5438 | F6: ='M&A Model'!B12 -> 0.05
A26: Visual 2: EPS Impact (Waterfall Chart)
A28: Step | B28: Base (invisible) | C28: Increase | D28: Decrease | E28: EPS Level (₹)
A29: Standalone EPS | B29: 0 | C29: ='M&A Model'!C29 -> 89.302251 | D29: 0 | E29: ='M&A Model'!C29 -> 89.302251
A30: Less: Interest Foregone (Cash) | B30: =E29-D30 -> 87.881586 | C30: 0 | D30: =('M&A Model'!C24/('M&A Model'!C24+'M&A Model'!C25))*('M&A Model'!C29-'M&A Model'!C31) -> 1.4206648 | E30: =E29-D30 -> 87.881586
A31: Less: Interest Expense (Debt) | B31: =E30-D31 -> 85.665349 | C31: 0 | D31: =('M&A Model'!C25/('M&A Model'!C24+'M&A Model'!C25))*('M&A Model'!C29-'M&A Model'!C31) -> 2.2162372 | E31: =E30-D31 -> 85.665349
A32: Combined EPS | B32: 0 | C32: ='M&A Model'!C31 -> 85.665349 | D32: 0 | E32: ='M&A Model'!C31 -> 85.665349
A34: Note: The ₹3.64 total per-share dilution is allocated between the two post-tax interest items in proportion to their ₹ Cr size, so the bars tie out exactly to the model's Standalone and Combined EPS (Sheet 'M&A Model', rows 24-31).
